llama_index/readers/microsoft_outlook/__init__.py
llama_index/readers/microsoft_outlook/base.py
llama_index_readers_microsoft_outlook-0.4.1.dist-info/METADATA
llama_index_readers_microsoft_outlook-0.4.1.dist-info/WHEEL
llama_index_readers_microsoft_outlook-0.4.1.dist-info/licenses/LICENSE
llama_index_readers_microsoft_outlook-0.4.1.dist-info/RECORD
