Metadata-Version: 2.4
Name: llama-index-readers-microsoft-outlook
Version: 0.4.1
Summary: llama-index readers microsoft outlook integration
Author-email: Your Name <you@example.com>
Maintainer: tevslin
License-Expression: MIT
License-File: LICENSE
Keywords: calendar,outlook
Requires-Python: <4.0,>=3.9
Requires-Dist: llama-index-core<0.15,>=0.13.0
